searchpi/__init__.py
searchpi/command_executer.py
searchpi/empty_logger.py
searchpi/errors.py
searchpi/main.py
searchpi-0.0.3.dist-info/LICENSE
searchpi-0.0.3.dist-info/METADATA
searchpi-0.0.3.dist-info/WHEEL
searchpi-0.0.3.dist-info/entry_points.txt
searchpi-0.0.3.dist-info/top_level.txt
searchpi-0.0.3.dist-info/RECORD
