Metadata-Version: 2.1
Name: searchpi
Version: 0.0.3
Summary: A command-line tool for searching your Raspberry Pi in a local network
Author-email: Evgeniy Blinov <zheni-b@yandex.ru>
Project-URL: Source, https://github.com/pomponchik/searchpi
Project-URL: Tracker, https://github.com/pomponchik/searchpi/issues
Classifier: Operating System :: MacOS :: MacOS X
Classifier: Operating System :: POSIX
Classifier: Programming Language :: Python :: 3.9
Classifier: Programming Language :: Python :: 3.10
Classifier: Programming Language :: Python :: 3.11
Classifier: Programming Language :: Python :: 3.12
Classifier: License :: OSI Approved :: MIT License
Classifier: Topic :: Software Development :: Libraries
Classifier: Topic :: Utilities
Classifier: Intended Audience :: System Administrators
Requires-Python: >=3.9
License-File: LICENSE
Requires-Dist: paramiko ==3.4.0
Requires-Dist: typer ==0.9.0
